Workbook

Sheet REPORTE
A1: Nro Guia | B1: Fecha ingreso a Planta | C1: Cliente | D1: Estado | E1: TIPO DE ESTADO | F1: GESTIÓN REALIZADA | G1: Remito | H1: Servicio | I1: Destinatario | J1: Domicilio | K1: Localidad | L1: Distribuidor Recorrido | M1: Recibio | N1: Documento | O1: CP | P1: FECHA ULTIMO ESTADO | Q1: Zona Destino
A2: =base!A2 -> 5526235 | B2: =base!BN2 -> 46148.584 | C2: =base!C2 -> ZETABURGOS SRL | D2: =base!E2 -> POD-ENTREGADA | E2: =base!BF2 -> ESTADO FINAL | G2: =base!G2 -> 46994624650 | H2: =base!I2 -> FLEX | I2: =base!S2 -> IvÃ¡n Aftalion | J2: =base!T2 -> Barrio La Lomada de Pilar 401 | K2: =base!U2 -> Del viso, pilar | L2: =base!Y2 -> 40464958 - HASSAN, RAFAEL | M2: =base!AH2 -> 0 | N2: =base!AI2 -> 0 | O2: =base!BA2 -> 1669 | P2: =base!BK2 -> 46148.738 | Q2: =base!BS2 -> NORTE N3
A3: =base!A3 -> 5528272 | B3: =base!BN3 -> 46148.459 | C3: =base!C3 -> ZETABURGOS SRL | D3: =base!E3 -> POD-ENTREGADA | E3: =base!BF3 -> ESTADO FINAL | G3: =base!G3 -> 46994045770-01 | H3: =base!I3 -> Same day | I3: =base!S3 -> 0 | J3: =base!T3 -> Calle Eva Peron 974 | K3: =base!U3 -> Ensenada | L3: =base!Y3 -> 41557955 - CONTRERAS, ANABELLA | M3: =base!AH3 -> 0 | N3: =base!AI3 -> 0 | O3: =base!BA3 -> 1925 | P3: =base!BK3 -> 46148.514 | Q3: =base!BS3 -> SUR S3
A4: =base!A4 -> 5528657 | B4: =base!BN4 -> 46148.583 | C4: =base!C4 -> ZETABURGOS SRL | D4: =base!E4 -> POD-ENTREGADA | E4: =base!BF4 -> ESTADO FINAL | G4: =base!G4 -> 46997213558 | H4: =base!I4 -> FLEX | I4: =base!S4 -> Federico VerriÃ¨ | J4: =base!T4 -> Del Alcanfor 1 SN 0 | K4: =base!U4 -> Nordelta | L4: =base!Y4 -> 36223447 - VILLAGRAN, FERNANDO | M4: =base!AH4 -> 0 | N4: =base!AI4 -> 0 | O4: =base!BA4 -> 1670 | P4: =base!BK4 -> 46148.856 | Q4: =base!BS4 -> NORTE N3
A5: =base!A5 -> 5529232 | B5: =base!BN5 -> 46148.583 | C5: =base!C5 -> ZETABURGOS SRL | D5: =base!E5 -> POD-ENTREGADA | E5: =base!BF5 -> ESTADO FINAL | G5: =base!G5 -> 46997885122 | H5: =base!I5 -> FLEX | I5: =base!S5 -> Dylan Junco | J5: =base!T5 -> General Francisco Fernandez de La Cruz 2490 | K5: =base!U5 -> Nueva Pompeya | L5: =base!Y5 -> 30036765 - FIGUEROA PR PM, SEBASTIAN | M5: =base!AH5 -> 0 | N5: =base!AI5 -> 0 | O5: =base!BA5 -> 1437 | P5: =base!BK5 -> 46148.741 | Q5: =base!BS5 -> CABA C4
A6: =base!A6 -> 5529356 | B6: =base!BN6 -> 46148.588 | C6: =base!C6 -> ZETABURGOS SRL | D6: =base!E6 -> POD-ENTREGADA | E6: =base!BF6 -> ESTADO FINAL | G6: =base!G6 -> 46997769697 | H6: =base!I6 -> FLEX | I6: =base!S6 -> Milagros Carballo | J6: =base!T6 -> Juan B. Justo 3323 | K6: =base!U6 -> ZÃ¡rate | L6: =base!Y6 -> 39829638 - ABAT, JULIAN | M6: =base!AH6 -> 0 | N6: =base!AI6 -> 0 | O6: =base!BA6 -> 2800 | P6: =base!BK6 -> 46148.824 | Q6: =base!BS6 -> NORTE N3
A7: =base!A7 -> 5530042 | B7: =base!BN7 -> 46148.582 | C7: =base!C7 -> ZETABURGOS SRL | D7: =base!E7 -> POD-ENTREGADA | E7: =base!BF7 -> ESTADO FINAL | G7: =base!G7 -> 46998809859 | H7: =base!I7 -> FLEX | I7: =base!S7 -> Muriel Cantlon | J7: =base!T7 -> Avenida Coronel Escalada 1200 | K7: =base!U7 -> Troncos del Talar | L7: =base!Y7 -> 32991335 - GOMEZ, FERNANDO | M7: =base!AH7 -> 0 | N7: =base!AI7 -> 0 | O7: =base!BA7 -> 1608 | P7: =base!BK7 -> 46148.705 | Q7: =base!BS7 -> NORTE N2
A8: =base!A8 -> 5530167 | B8: =base!BN8 -> 46148.589 | C8: =base!C8 -> ZETABURGOS SRL | D8: =base!E8 -> POD-ENTREGADA | E8: =base!BF8 -> ESTADO FINAL | G8: =base!G8 -> 46999048779 | H8: =base!I8 -> FLEX | I8: =base!S8 -> NoemÃ­ gutierrez | J8: =base!T8 -> Calle Guiraldes 9 | K8: =base!U8 -> Alejandro Korn | L8: =base!Y8 -> 28407972 - GARCIA-FLOTA GRUPO FS, ARIEL | M8: =base!AH8 -> 0 | N8: =base!AI8 -> 0 | O8: =base!BA8 -> 1864 | P8: =base!BK8 -> 46148.862 | Q8: =base!BS8 -> SUR S3
A9: =base!A9 -> 5530417 | B9: =base!BN9 -> 46148.583 | C9: =base!C9 -> ZETABURGOS SRL | D9: =base!E9 -> POD-ENTREGADA | E9: =base!BF9 -> ESTADO FINAL | G9: =base!G9 -> 46999521825 | H9: =base!I9 -> FLEX | I9: =base!S9 -> Maria Victoria Romero | J9: =base!T9 -> Calle Lavalle 607 | K9: =base!U9 -> LujÃ¡n | L9: =base!Y9 -> 17687556 - SOTELO, MIRIAM | M9: =base!AH9 -> 0 | N9: =base!AI9 -> 0 | O9: =base!BA9 -> 6700 | P9: =base!BK9 -> 46148.794 | Q9: =base!BS9 -> OESTE O3
A10: =base!A10 -> 5530492 | B10: =base!BN10 -> 46148.582 | C10: =base!C10 -> ZETABURGOS SRL | D10: =base!E10 -> RC-En ruta para su entrega | E10: =base!BF10 -> ESTADO PENDIENTE | G10: =base!G10 -> 46999937136 | H10: =base!I10 -> FLEX | I10: =base!S10 -> Julieta Lambertini | J10: =base!T10 -> Avenida General Las Heras 4009 | K10: =base!U10 -> Palermo | L10: =base!Y10 -> 22963430 - BOCCUTI, ROSA PAULINA | M10: =base!AH10 -> 0 | N10: =base!AI10 -> 0 | O10: =base!BA10 -> 1425 | P10: =base!BK10 -> 46149 | Q10: =base!BS10 -> CABA C14
A11: =base!A11 -> 5530588 | B11: =base!BN11 -> 46148.585 | C11: =base!C11 -> ZETABURGOS SRL | D11: =base!E11 -> POD-ENTREGADA | E11: =base!BF11 -> ESTADO FINAL | G11: =base!G11 -> 46999869579 | H11: =base!I11 -> FLEX | I11: =base!S11 -> jose jorge silva | J11: =base!T11 -> ruta 58 18500 | K11: =base!U11 -> San Vicente | L11: =base!Y11 -> 42089762 - ARRUA, LEANDRO | M11: =base!AH11 -> 0 | N11: =base!AI11 -> 0 | O11: =base!BA11 -> 1865 | P11: =base!BK11 -> 46148.797 | Q11: =base!BS11 -> SUR S3
A12: =base!A12 -> 5531085 | B12: =base!BN12 -> 46148.584 | C12: =base!C12 -> ZETABURGOS SRL | D12: =base!E12 -> POD-ENTREGADA | E12: =base!BF12 -> ESTADO FINAL | G12: =base!G12 -> 47000952097 | H12: =base!I12 -> FLEX | I12: =base!S12 -> colin campbell | J12: =base!T12 -> Calle Italia 5043 | K12: =base!U12 -> dique lujan | L12: =base!Y12 -> 32642159 - GONZALEZ, JUAN MARCELO | M12: =base!AH12 -> 0 | N12: =base!AI12 -> 0 | O12: =base!BA12 -> 1622 | P12: =base!BK12 -> 46148.756 | Q12: =base!BS12 -> NORTE N2B
A13: =base!A13 -> 5531316 | B13: =base!BN13 -> 46148.585 | C13: =base!C13 -> ZETABURGOS SRL | D13: =base!E13 -> POD-ENTREGADA | E13: =base!BF13 -> ESTADO FINAL | G13: =base!G13 -> 47001190219 | H13: =base!I13 -> FLEX | I13: =base!S13 -> luis martinez | J13: =base!T13 -> Calle Santa Margarita 2350 | K13: =base!U13 -> Del Viso | L13: =base!Y13 -> 32642159 - GONZALEZ, JUAN MARCELO | M13: =base!AH13 -> 0 | N13: =base!AI13 -> 0 | O13: =base!BA13 -> 1669 | P13: =base!BK13 -> 46148.846 | Q13: =base!BS13 -> NORTE N3
... A189: =base!A189 -> 0 | B189: =base!BN189 -> 0 | C189: =base!C189 -> 0 | D189: =base!E189 -> 0 | E189: =base!BF189 -> 0 | G189: =base!G189 -> 0 | H189: =base!I189 -> 0 | I189: =base!S189 -> 0 | J189: =base!T189 -> 0 | K189: =base!U189 -> 0 | L189: =base!Y189 -> 0 | M189: =base!AH189 -> 0 | N189: =base!AI189 -> 0 | O189: =base!BA189 -> 0 | P189: =base!BK189 -> 0 | Q189: =base!BS189 -> 0

Sheet base
A1: Nro Guia | B1: Fecha | C1: Cliente | D1: Sucursal | E1: Estado | F1: Motivo | G1: Remito | H1: Guia Agente | I1: Servicio | J1: Tiempo | K1: Localidad Origen | L1: Localidad Destino | M1: Destino | N1: Peso | O1: Bultos | P1: Importe | Q1: Valor Declarado | R1: Empresa | S1: Destinatario | T1: Domicilio | U1: Localidad | V1: Provincia | W1: Email | X1: Horario | Y1: Distribuidor Recorrido | Z1: Distribuidor Origen | AA1: Distribuidor Destino | AB1: Fecha Planilla | AC1: Nro. Planilla | AD1: Fecha Rendicion | AE1: Nro. Rendicion | AF1: Fecha Pactada | AG1: Fecha Entrega | AH1: Recibio | AI1: Documento | AJ1: Lote | AK1: Contrareembolso | AL1: Other Info | AM1: Obs 1 | AN1: Obs 2 | AO1: Nro.Socio | AP1: Nro.Prestador | AQ1: Usuario | AR1: Peso Volumetrico | AS1: Volumen | AT1: Ceco | AU1: Importe Urgente | AV1: Kg Exceso | AW1: Importe Exceso | AX1: Sector | AY1: Trabajo | AZ1: Fecha Repactacion | BA1: CP | BB1: PLANILLA FACTURADO | BC1: CONSTANCIA RETIRO | BD1: SUCURSAL ORIGEN | BE1: SUCURSAL DESTINO | BF1: GRUPO | BG1: COM.OBS 3 | BH1: COM.OBS 4 | BI1: COM.OTHER INFO | BJ1: COM.CELULAR | BK1: FECHA ULTIMO ESTADO | BL1: Precinto | BM1: Codigo Sucursal | BN1: Fecha Ingreso a Planta | BO1: Datos Envios Obs | BP1: Pago En | BQ1: Codigo Sucursal Naranja Devolucion | BR1: Descripcion Sucursal Naranja Devolucion | BS1: Zona Destino | BT1: Sub Zona Destino | BU1: Nombre Fantasia | BV1: Nro.Liquidacion | BW1: Canal
A2: 5526235 | B2: 46147 | C2: ZETABURGOS SRL | D2: TIENDA OBJETOS SUC. CABA | E2: POD-ENTREGADA | F2: Cambio notificado por MFLEX | G2: 46994624650 | H2: 2000016282890952 | I2: FLEX | N2: 1.7 | O2: 1 | P2: 9426.31 | Q2: 27741 | S2: IvÃ¡n Aftalion | T2: Barrio La Lomada de Pilar 401 | U2: Del viso, pilar | V2: Buenos Aires | Y2: 40464958 - HASSAN, RAFAEL | AB2: 46148 | AC2: 80018 | AF2: 46148 | AG2: 46148.738 | AK2: 0 | AM2: Tipo domicilio: Particular. Km 45 panamericana ramal pilar | AN2: Tipo domicilio: Particular. Km 45 panamericana ramal pilar | AQ2: tiendaobjetos | AR2: 5,265 | AS2: 5.265 | AX2: PAQUETERIA | BA2: 1669 | BF2: ESTADO FINAL | BG2: Tipo domicilio: Particular. Km 45 panamericana ramal pilar | BJ2: XXXXXXX | BK2: 46148.738 | BN2: 46148.584 | BO2: Pedido creado desde mercadoflex. Api v2 | BP2: ORIGEN | BS2: NORTE N3 | BT2: Del Viso | BU2: Tienda Objetos | BW2: Mflex
A3: 5528272 | B3: 46147 | C3: ZETABURGOS SRL | D3: TIENDA OBJETOS SUC. CABA | E3: POD-ENTREGADA | G3: 46994045770-01 | I3: Same day | N3: 1 | O3: 1 | P3: 9426.31 | T3: Calle Eva Peron 974 | U3: Ensenada | V3: BUENOS AIRES | Y3: 41557955 - CONTRERAS, ANABELLA | AB3: 46148 | AC3: 79950 | AF3: 46148 | AG3: 46148.514 | AQ3: gracielaalfonso | AR3: 0 | AS3: 1 | AV3: 0 | AW3: 0 | AX3: PAQUETERIA | BA3: 1925 | BD3: SMARTPOST | BE3: SMARTPOST | BF3: ESTADO FINAL | BK3: 46148.514 | BN3: 46148.459 | BP3: ORIGEN | BS3: SUR S3 | BT3: Ensenada | BU3: Tienda Objetos | BW3: CARGA MANUAL
A4: 5528657 | B4: 46147 | C4: ZETABURGOS SRL | D4: TIENDA OBJETOS SUC. CABA | E4: POD-ENTREGADA | F4: Cambio notificado por MFLEX | G4: 46997213558 | H4: 2000012829930141 | I4: FLEX | N4: 0.66 | O4: 2 | P4: 9426.31 | Q4: 17176 | S4: Federico VerriÃ¨ | T4: Del Alcanfor 1 SN 0 | U4: Nordelta | V4: Buenos Aires | Y4: 36223447 - VILLAGRAN, FERNANDO | AB4: 46148 | AC4: 79916 | AF4: 46148 | AG4: 46148.856 | AK4: 0 | AM4: Tipo domicilio: Particular. Barrio Las Tipas Referencia: Indicar en puerta de seguridad, Lote 150. | AN4: Tipo domicilio: Particular. Barrio Las Tipas Referencia: Indicar en puerta de seguridad, Lote 150. | AQ4: tiendaobjetos | AR4: 11,718 | AS4: 11.718 | AX4: PAQUETERIA | BA4: 1670 | BE4: SMARTPOST | BF4: ESTADO FINAL | BG4: Tipo domicilio: Particular. Barrio Las Tipas Referencia: Indicar en puerta de seguridad, Lote 150. | BJ4: XXXXXXX | BK4: 46148.856 | BN4: 46148.583 | BO4: Pedido creado desde mercadoflex. Api v2 | BP4: ORIGEN | BS4: NORTE N3 | BT4: Nordelta Tigre | BU4: Tienda Objetos | BW4: Mflex
A5: 5529232 | B5: 46147 | C5: ZETABURGOS SRL | D5: TIENDA OBJETOS SUC. CABA | E5: POD-ENTREGADA | F5: Cambio notificado por MFLEX | G5: 46997885122 | H5: 2000012831401499 | I5: FLEX | N5: 336 | O5: 20 | P5: 3919.34 | Q5: 259220 | S5: Dylan Junco | T5: General Francisco Fernandez de La Cruz 2490 | U5: Nueva Pompeya | V5: Capital Federal | Y5: 30036765 - FIGUEROA PR PM, SEBASTIAN | AB5: 46148 | AC5: 79901 | AF5: 46148 | AG5: 46148.74 | AK5: 0 | AM5: Tipo domicilio: Comercial. Referencia: Lugar de trabajo, abierto hasta la 18hs, Frente al cancha de san Lorenzo | AN5: Tipo domicilio: Comercial. Referencia: Lugar de trabajo, abierto hasta la 18hs, Frente al cancha de san Lorenzo | AQ5: tiendaobjetos | AR5: 176 | AS5: 336 | AX5: PAQUETERIA | BA5: 1437 | BF5: ESTADO FINAL | BG5: Tipo domicilio: Comercial. Referencia: Lugar de trabajo, abierto hasta la 18hs, Frente al cancha de san Lorenzo | BJ5: XXXXXXX | BK5: 46148.741 | BN5: 46148.583 | BO5: Pedido creado desde mercadoflex. Api v2 | BP5: ORIGEN | BS5: CABA C4 | BT5: CABA C4 | BU5: Tienda Objetos | BW5: Mflex
A6: 5529356 | B6: 46147 | C6: ZETABURGOS SRL | D6: TIENDA OBJETOS SUC. CABA | E6: POD-ENTREGADA | F6: Cambio notificado por MFLEX | G6: 46997769697 | H6: 2000016290176042 | I6: FLEX | N6: 2.95 | O6: 1 | P6: 9426.31 | Q6: 47732.12 | S6: Milagros Carballo | T6: Juan B. Justo 3323 | U6: ZÃ¡rate | V6: Buenos Aires | Y6: 39829638 - ABAT, JULIAN | AB6: 46148 | AC6: 79923 | AF6: 46148 | AG6: 46148.824 | AK6: 0 | AM6: Tipo domicilio: Particular. Prefabricada gris Referencia: Entre 32 y 34 casa prefabricada gris Entre: 32 y 34 | AN6: Tipo domicilio: Particular. Prefabricada gris Referencia: Entre 32 y 34 casa prefabricada gris Entre: 32 y 34 | AQ6: tiendaobjetos | AR6: 4,95 | AS6: 4.95 | AX6: PAQUETERIA | BA6: 2800 | BE6: SMARTPOST | BF6: ESTADO FINAL | BG6: Tipo domicilio: Particular. Prefabricada gris Referencia: Entre 32 y 34 casa prefabricada gris Entre: 32 y 34 | BJ6: XXXXXXX | BK6: 46148.824 | BN6: 46148.588 | BO6: Pedido creado desde mercadoflex. Api v2 | BP6: ORIGEN | BS6: NORTE N3 | BT6: Zarate | BU6: Tienda Objetos | BW6: Mflex
A7: 5530042 | B7: 46147 | C7: ZETABURGOS SRL | D7: TIENDA OBJETOS SUC. CABA | E7: POD-ENTREGADA | F7: Cambio notificado por MFLEX | G7: 46998809859 | H7: 2000012834108941 | I7: FLEX | N7: 0.5 | O7: 1 | P7: 8709.92 | Q7: 39463 | S7: Muriel Cantlon | T7: Avenida Coronel Escalada 1200 | U7: Troncos del Talar | V7: Buenos Aires | Y7: 32991335 - GOMEZ, FERNANDO | AB7: 46148 | AC7: 80005 | AF7: 46148 | AG7: 46148.705 | AK7: 0 | AM7: Tipo domicilio: Particular. Lote 337 Referencia: Barrio Laguna del Sol | AN7: Tipo domicilio: Particular. Lote 337 Referencia: Barrio Laguna del Sol | AQ7: tiendaobjetos | AR7: 1,512 | AS7: 1.512 | AX7: PAQUETERIA | BA7: 1608 | BF7: ESTADO FINAL | BG7: Tipo domicilio: Particular. Lote 337 Referencia: Barrio Laguna del Sol | BJ7: XXXXXXX | BK7: 46148.705 | BN7: 46148.582 | BO7: Pedido creado desde mercadoflex. Api v2 | BP7: ORIGEN | BS7: NORTE N2 | BT7: Troncos Del Talar | BU7: Tienda Objetos | BW7: Mflex
A8: 5530167 | B8: 46147 | C8: ZETABURGOS SRL | D8: TIENDA OBJETOS SUC. CABA | E8: POD-ENTREGADA | F8: Cambio notificado por MFLEX | G8: 46999048779 | H8: 2000012834665573 | I8: FLEX | N8: 0.46 | O8: 1 | P8: 9426.31 | Q8: 26528 | S8: NoemÃ­ gutierrez | T8: Calle Guiraldes 9 | U8: Alejandro Korn | V8: Buenos Aires | Y8: 28407972 - GARCIA-FLOTA GRUPO FS, ARIEL | AB8: 46148 | AC8: 79955 | AF8: 46148 | AG8: 46148.862 | AK8: 0 | AM8: Tipo domicilio: Particular. Referencia: casa blanca justo en la esquina rejas rojas oxidadas Entre: mitre 810 y kennedy | AN8: Tipo domicilio: Particular. Referencia: casa blanca justo en la esquina rejas rojas oxidadas Entre: mitre 810 y kennedy | AQ8: tiendaobjetos | AR8: 0,4875 | AS8: 0.4875 | AX8: PAQUETERIA | BA8: 1864 | BE8: SMARTPOST | BF8: ESTADO FINAL | BG8: Tipo domicilio: Particular. Referencia: casa blanca justo en la esquina rejas rojas oxidadas Entre: mitre 810 y kennedy | BJ8: XXXXXXX | BK8: 46148.862 | BN8: 46148.589 | BO8: Pedido creado desde mercadoflex. Api v2 | BP8: ORIGEN | BS8: SUR S3 | BT8: Alejandro Korn | BU8: Tienda Objetos | BW8: Mflex
A9: 5530417 | B9: 46147 | C9: ZETABURGOS SRL | D9: TIENDA OBJETOS SUC. CABA | E9: POD-ENTREGADA | F9: Cambio notificado por MFLEX | G9: 46999521825 | H9: 2000012835756717 | I9: FLEX | N9: 0.72 | O9: 2 | P9: 9426.31 | Q9: 20301 | S9: Maria Victoria Romero | T9: Calle Lavalle 607 | U9: LujÃ¡n | V9: Buenos Aires | Y9: 17687556 - SOTELO, MIRIAM | AB9: 46148 | AC9: 80039 | AF9: 46148 | AG9: 46148.794 | AK9: 0 | AM9: Tipo domicilio: Particular. 1c | AN9: Tipo domicilio: Particular. 1c | AQ9: tiendaobjetos | AR9: 2,48 | AS9: 2.48 | AX9: PAQUETERIA | BA9: 6700 | BE9: SMARTPOST | BF9: ESTADO FINAL | BG9: Tipo domicilio: Particular. 1c | BJ9: XXXXXXX | BK9: 46148.794 | BN9: 46148.583 | BO9: Pedido creado desde mercadoflex. Api v2 | BP9: ORIGEN | BS9: OESTE O3 | BT9: LUJAN | BU9: Tienda Objetos | BW9: Mflex
A10: 5530492 | B10: 46147 | C10: ZETABURGOS SRL | D10: TIENDA OBJETOS SUC. CABA | E10: RC-En ruta para su entrega | G10: 46999937136 | H10: 2000012836092415 | I10: FLEX | N10: 3.6 | O10: 2 | P10: 3919.34 | Q10: 10998 | S10: Julieta Lambertini | T10: Avenida General Las Heras 4009 | U10: Palermo | V10: Capital Federal | Y10: 22963430 - BOCCUTI, ROSA PAULINA | AB10: 46149 | AC10: 80070 | AF10: 46148 | AG10: 46148.819 | AK10: 0 | AM10: Tipo domicilio: Particular. 1 D | AN10: Tipo domicilio: Particular. 1 D | AQ10: tiendaobjetos | AR10: 8,16 | AS10: 8.16 | AX10: PAQUETERIA | BA10: 1425 | BE10: SMARTPOST | BF10: ESTADO PENDIENTE | BG10: Tipo domicilio: Particular. 1 D | BJ10: XXXXXXX | BK10: 46149 | BN10: 46148.582 | BO10: Pedido creado desde mercadoflex. Api v2 | BP10: ORIGEN | BS10: CABA C14 | BT10: CABA C14 | BU10: Tienda Objetos | BW10: Mflex
A11: 5530588 | B11: 46147 | C11: ZETABURGOS SRL | D11: TIENDA OBJETOS SUC. CABA | E11: POD-ENTREGADA | F11: Cambio notificado por MFLEX | G11: 46999869579 | H11: 2000012836572973 | I11: FLEX | N11: 2 | O11: 10 | P11: 9426.31 | Q11: 45420 | S11: jose jorge silva | T11: ruta 58 18500 | U11: San Vicente | V11: Buenos Aires | Y11: 42089762 - ARRUA, LEANDRO | AB11: 46148 | AC11: 80037 | AF11: 46148 | AG11: 46148.797 | AK11: 0 | AM11: Tipo domicilio: Particular. lote 231 Referencia: barrio lagos de san eliseo Entre: rivadavia y capdevilla | AN11: Tipo domicilio: Particular. lote 231 Referencia: barrio lagos de san eliseo Entre: rivadavia y capdevilla | AQ11: tiendaobjetos | AR11: 9,6 | AS11: 9.6 | AX11: PAQUETERIA | BA11: 1865 | BE11: SMARTPOST | BF11: ESTADO FINAL | BG11: Tipo domicilio: Particular. lote 231 Referencia: barrio lagos de san eliseo Entre: rivadavia y capdevilla | BJ11: XXXXXXX | BK11: 46148.797 | BN11: 46148.585 | BO11: Pedido creado desde mercadoflex. Api v2 | BP11: ORIGEN | BS11: SUR S3 | BT11: San Vicente | BU11: Tienda Objetos | BW11: Mflex
A12: 5531085 | B12: 46148 | C12: ZETABURGOS SRL | D12: TIENDA OBJETOS SUC. CABA | E12: POD-ENTREGADA | F12: Cambio notificado por MFLEX | G12: 47000952097 | H12: 2000012839131915 | I12: FLEX | N12: 5.22 | O12: 3 | P12: 9426.31 | Q12: 52749 | S12: colin campbell | T12: Calle Italia 5043 | U12: dique lujan | V12: Buenos Aires | Y12: 32642159 - GONZALEZ, JUAN MARCELO | AB12: 46148 | AC12: 79989 | AF12: 46149 | AG12: 46148.756 | AK12: 0 | AM12: Tipo domicilio: Particular. lote 640 Referencia: Barrio san isidro labrador | AN12: Tipo domicilio: Particular. lote 640 Referencia: Barrio san isidro labrador | AQ12: tiendaobjetos | AR12: 10,5105 | AS12: 10.5105 | AX12: PAQUETERIA | BA12: 1622 | BF12: ESTADO FINAL | BG12: Tipo domicilio: Particular. lote 640 Referencia: Barrio san isidro labrador | BJ12: XXXXXXX | BK12: 46148.756 | BN12: 46148.584 | BO12: Pedido creado desde mercadoflex. Api v2 | BP12: ORIGEN | BS12: NORTE N2B | BT12: Dique Lujan | BU12: Tienda Objetos | BW12: Mflex
A13: 5531316 | B13: 46148 | C13: ZETABURGOS SRL | D13: TIENDA OBJETOS SUC. CABA | E13: POD-ENTREGADA | F13: Cambio notificado por MFLEX | G13: 47001190219 | H13: 2000012839597353 | I13: FLEX | N13: 0.36 | O13: 1 | P13: 9426.31 | Q13: 20612 | S13: luis martinez | T13: Calle Santa Margarita 2350 | U13: Del Viso | V13: Buenos Aires | Y13: 32642159 - GONZALEZ, JUAN MARCELO | AB13: 46148 | AC13: 79989 | AF13: 46149 | AG13: 46148.846 | AK13: 0 | AM13: Tipo domicilio: Particular. casa Referencia: santa margarita esquina pirovano portÃ³n de chapa blanco justo en la esquina Entre: pirovano y mansilla | AN13: Tipo domicilio: Particular. casa Referencia: santa margarita esquina pirovano portÃ³n de chapa blanco justo en la esquina Entre: pirovano y mansilla | AQ13: tiendaobjetos | AR13: 0,486 | AS13: 0.486 | AX13: PAQUETERIA | BA13: 1669 | BF13: ESTADO FINAL | BG13: Tipo domicilio: Particular. casa Referencia: santa margarita esquina pirovano portÃ³n de chapa blanco justo en la esquina Entre: pirovano y mansilla | BJ13: XXXXXXX | BK13: 46148.846 | BN13: 46148.585 | BO13: Pedido creado desde mercadoflex. Api v2 | BP13: ORIGEN | BS13: NORTE N3 | BT13: Del Viso | BU13: Tienda Objetos | BW13: Mflex
A14: 5531423 | B14: 46148 | C14: ZETABURGOS SRL | D14: TIENDA OBJETOS SUC. CABA | E14: POD-ENTREGADA | F14: Cambio notificado por MFLEX | G14: 47001328931 | H14: 2000012839871135 | I14: FLEX | N14: 2 | O14: 1 | P14: 3919.34 | Q14: 28140 | S14: Tune (Piso 7) | T14: Calle Tucuman 117 | U14: San NicolÃ¡s | V14: Capital Federal | Y14: 29218662 - SILVA, ARIEL | AB14: 46148 | AC14: 80006 | AF14: 46149 | AG14: 46148.651 | AK14: 0 | AM14: Tipo domicilio: Comercial. 7 Referencia: 7 | AN14: Tipo domicilio: Comercial. 7 Referencia: 7 | AQ14: tiendaobjetos | AR14: 8,32 | AS14: 8.32 | AX14: PAQUETERIA | BA14: 1049 | BF14: ESTADO FINAL | BG14: Tipo domicilio: Comercial. 7 Referencia: 7 | BJ14: XXXXXXX | BK14: 46148.652 | BN14: 46148.588 | BO14: Pedido creado desde mercadoflex. Api v2 | BP14: ORIGEN | BS14: CABA C1 | BT14: CABA C1 | BU14: Tienda Objetos | BW14: Mflex
A15: 5531424 | B15: 46148 | C15: ZETABURGOS SRL | D15: TIENDA OBJETOS SUC. CABA | E15: POD-ENTREGADA | F15: Cambio notificado por MFLEX | G15: 47001603072 | H15: 2000012839871139 | I15: FLEX | N15: 2 | O15: 1 | P15: 3919.34 | Q15: 28140 | S15: Tune (Piso 7) | T15: Calle Tucuman 117 | U15: San NicolÃ¡s | V15: Capital Federal | Y15: 29218662 - SILVA, ARIEL | AB15: 46148 | AC15: 80006 | AF15: 46149 | AG15: 46148.651 | AK15: 0 | AM15: Tipo domicilio: Comercial. 7 Referencia: 7 | AN15: Tipo domicilio: Comercial. 7 Referencia: 7 | AQ15: tiendaobjetos | AR15: 8,32 | AS15: 8.32 | AX15: PAQUETERIA | BA15: 1049 | BF15: ESTADO FINAL | BG15: Tipo domicilio: Comercial. 7 Referencia: 7 | BJ15: XXXXXXX | BK15: 46148.652 | BN15: 46148.588 | BO15: Pedido creado desde mercadoflex. Api v2 | BP15: ORIGEN | BS15: CABA C1 | BT15: CABA C1 | BU15: Tienda Objetos | BW15: Mflex
A16: 5531425 | B16: 46148 | C16: ZETABURGOS SRL | D16: TIENDA OBJETOS SUC. CABA | E16: POD-ENTREGADA | F16: Cambio notificado por MFLEX | G16: 47001328901 | H16: 2000012839871137 | I16: FLEX | N16: 2 | O16: 1 | P16: 3919.34 | Q16: 28140 | S16: Tune (Piso 7) | T16: Calle Tucuman 117 | U16: San NicolÃ¡s | V16: Capital Federal | Y16: 29218662 - SILVA, ARIEL | AB16: 46148 | AC16: 80006 | AF16: 46149 | AG16: 46148.652 | AK16: 0 | AM16: Tipo domicilio: Comercial. 7 Referencia: 7 | AN16: Tipo domicilio: Comercial. 7 Referencia: 7 | AQ16: tiendaobjetos | AR16: 8,32 | AS16: 8.32 | AX16: PAQUETERIA | BA16: 1049 | BF16: ESTADO FINAL | BG16: Tipo domicilio: Comercial. 7 Referencia: 7 | BJ16: XXXXXXX | BK16: 46148.652 | BN16: 46148.588 | BO16: Pedido creado desde mercadoflex. Api v2 | BP16: ORIGEN | BS16: CABA C1 | BT16: CABA C1 | BU16: Tienda Objetos | BW16: Mflex
A17: 5531770 | B17: 46148 | C17: ZETABURGOS SRL | D17: TIENDA OBJETOS SUC. CABA | E17: POD-ENTREGADA | F17: Cambio notificado por MFLEX | G17: 47001821812 | H17: 2000012840312751 | I17: FLEX | N17: 5.19 | O17: 3 | P17: 3919.34 | Q17: 58827 | S17: Pedro Sanchez | T17: Arevalo 3063 | U17: Palermo | V17: Capital Federal | Y17: 22963430 - BOCCUTI, ROSA PAULINA | AB17: 46148 | AC17: 79921 | AF17: 46149 | AG17: 46148.889 | AK17: 0 | AM17: Tipo domicilio: Particular. Piso 3 depto fondo Referencia: Piso 3 depto f de fondo. Por favor llamar ya que el portero funciona mÃ¡s o menos | AN17: Tipo domicilio: Particular. Piso 3 depto fondo Referencia: Piso 3 depto f de fondo. Por favor llamar ya que el portero funciona mÃ¡s o menos | AQ17: tiendaobjetos | AR17: 9,768 | AS17: 9.768 | AX17: PAQUETERIA | BA17: 1425 | BE17: SMARTPOST | BF17: ESTADO FINAL | BG17: Tipo domicilio: Particular. Piso 3 depto fondo Referencia: Piso 3 depto f de fondo. Por favor llamar ya que el portero funciona mÃ¡s o menos | BJ17: XXXXXXX | BK17: 46148.889 | BN17: 46148.582 | BO17: Pedido creado desde mercadoflex. Api v2 | BP17: ORIGEN | BS17: CABA C14 | BT17: CABA C14 | BU17: Tienda Objetos | BW17: Mflex
A18: 5531802 | B18: 46148 | C18: ZETABURGOS SRL | D18: TIENDA OBJETOS SUC. CABA | E18: POD-ENTREGADA | F18: Cambio notificado por MFLEX | G18: 47001589639 | H18: 2000012840396909 | I18: FLEX | N18: 2.8 | O18: 4 | P18: 3919.34 | Q18: 25592 | S18: linda Levy | T18: Avenida del Libertador 2213 | U18: Palermo | V18: Capital Federal | Y18: 22963430 - BOCCUTI, ROSA PAULINA | AB18: 46148 | AC18: 79921 | AF18: 46149 | AG18: 46148.857 | AK18: 0 | AM18: Tipo domicilio: Particular. 3 Referencia: av del libertador | AN18: Tipo domicilio: Particular. 3 Referencia: av del libertador | AQ18: tiendaobjetos | AR18: 10,8 | AS18: 10.8 | AX18: PAQUETERIA | BA18: 1425 | BE18: SMARTPOST | BF18: ESTADO FINAL | BG18: Tipo domicilio: Particular. 3 Referencia: av del libertador | BJ18: XXXXXXX | BK18: 46148.857 | BN18: 46148.585 | BO18: Pedido creado desde mercadoflex. Api v2 | BP18: ORIGEN | BS18: CABA C14 | BT18: CABA C14 | BU18: Tienda Objetos | BW18: Mflex
A19: 5531981 | B19: 46148 | C19: ZETABURGOS SRL | D19: TIENDA OBJETOS SUC. CABA | E19: RC-En ruta para su entrega | G19: 2000016198948346-c | H19: 2000016198948346 | I19: Same day | N19: 1 | O19: 1 | P19: 9426.31 | S19: Karina Soto (SOTOKARINA33) | T19: Calle 6 2739 | U19: Manuel B Gonnet | V19: BUENOS AIRES | Y19: 41557955 - CONTRERAS, ANABELLA | AB19: 46149 | AC19: 80099 | AF19: 46149 | AG19: 46148.746 | AQ19: tiendaobjetos | AR19: 0,25 | AS19: 1 | AV19: 0 | AW19: 0 | AX19: PAQUETERIA | BA19: 1897 | BE19: SMARTPOST | BF19: ESTADO PENDIENTE | BI19: Paredonblanco porton negro de chapa Entre: 504 y 505 | FRÃGIL | TRAER CAMBIO | BJ19: +54 9 2215 63-6700 | BK19: 46149 | BN19: 46148.588 | BP19: ORIGEN | BS19: SUR S3 | BT19: Gonnet | BU19: Tienda Objetos | BW19: CARGA MANUAL
A20: 5532510 | B20: 46148 | C20: ZETABURGOS SRL | D20: TIENDA OBJETOS SUC. CABA | E20: POD-ENTREGADA | F20: Cambio notificado por MFLEX | G20: 47002610904 | H20: 2000012831701679 | I20: FLEX | N20: 2.72 | O20: 2 | P20: 3919.34 | Q20: 29194 | S20: Cristian Ricardo Corbellini | T20: Calle Pea 3083 | U20: Recoleta | V20: Capital Federal | Y20: 96117351P - TORREZ PR PM, MARBELIS | AB20: 46148 | AC20: 79986 | AF20: 46149 | AG20: 46148.678 | AK20: 0 | AM20: Tipo domicilio: Particular. 6 D Referencia: Entregar a la seguridad | AN20: Tipo domicilio: Particular. 6 D Referencia: Entregar a la seguridad | AQ20: tiendaobjetos | AR20: 4,62 | AS20: 4.62 | AX20: PAQUETERIA | BA20: 1425 | BF20: ESTADO FINAL | BG20: Tipo domicilio: Particular. 6 D Referencia: Entregar a la seguridad | BJ20: XXXXXXX | BK20: 46148.678 | BN20: 46148.583 | BO20: Pedido creado desde mercadoflex. Api v2 | BP20: ORIGEN | BS20: CABA C14 | BT20: CABA C14 | BU20: Tienda Objetos | BW20: Mflex
A21: 5532564 | B21: 46148 | C21: ZETABURGOS SRL | D21: TIENDA OBJETOS SUC. CABA | E21: POD-ENTREGADA | F21: Cambio notificado por MFLEX | G21: 47002397055 | H21: 2000012842098097 | I21: FLEX | N21: 0.42 | O21: 1 | P21: 9426.31 | Q21: 41259 | S21: Agustin Miguel Cikes | T21: Everlinks Golf y Country Club - Lote 139 SN 0 | U21: LujÃ¡n | V21: Buenos Aires | Y21: 17687556 - SOTELO, MIRIAM | AB21: 46148 | AC21: 80039 | AF21: 46149 | AG21: 46148.869 | AK21: 0 | AM21: Tipo domicilio: Particular. | AN21: Tipo domicilio: Particular. | AQ21: tiendaobjetos | AR21: 0,504 | AS21: 0.504 | AX21: PAQUETERIA | BA21: 6702 | BE21: SMARTPOST | BF21: ESTADO FINAL | BG21: Tipo domicilio: Particular. | BJ21: XXXXXXX | BK21: 46148.869 | BN21: 46148.583 | BO21: Pedido creado desde mercadoflex. Api v2 | BP21: ORIGEN | BS21: OESTE O3 | BT21: LUJAN | BU21: Tienda Objetos | BW21: Mflex
A22: 5532834 | B22: 46148 | C22: ZETABURGOS SRL | D22: TIENDA OBJETOS SUC. CABA | E22: POD-ENTREGADA | F22: Cambio notificado por MFLEX | G22: 47002986994 | H22: 2000012842785329 | I22: FLEX | N22: 1.2 | O22: 1 | P22: 3919.34 | Q22: 32017 | S22: Gustavo Rodriguez | T22: Avenida Intendente Bullrich 481 | U22: Palermo | V22: Capital Federal | Y22: 37251859 - CASTELLANOS, LUIS FRANCO | AB22: 46148 | AC22: 79968 | AF22: 46149 | AG22: 46148.79 | AK22: 0 | AM22: Tipo domicilio: Comercial. Referencia: Es para la FundaciÃ³n El Uno Grande, entregarla en su oficina una vez que ingresÃ³ al Regimiento, por favor. Gracias. | AN22: Tipo domicilio: Comercial. Referencia: Es para la FundaciÃ³n El Uno Grande, entregarla en su oficina una vez que ingresÃ³ al Regimiento, por favor. Gracias. | AQ22: tiendaobjetos | AR22: 1,29 | AS22: 1.29 | AX22: PAQUETERIA | BA22: 1425 | BE22: SMARTPOST | BF22: ESTADO FINAL | BG22: Tipo domicilio: Comercial. Referencia: Es para la FundaciÃ³n El Uno Grande, entregarla en su oficina una vez que ingresÃ³ al Regimiento, por favor. Gracias. | BJ22: XXXXXXX | BK22: 46148.79 | BN22: 46148.586 | BO22: Pedido creado desde mercadoflex. Api v2 | BP22: ORIGEN | BS22: CABA C14 | BT22: CABA C14 | BU22: Tienda Objetos | BW22: Mflex
A23: 5533020 | B23: 46148 | C23: ZETABURGOS SRL | D23: TIENDA OBJETOS SUC. CABA | E23: POD-ENTREGADA | F23: Cambio notificado por MFLEX | G23: 47002363688 | H23: 2000012841448793 | I23: FLEX | N23: 14.4 | O23: 4 | P23: 3919.34 | Q23: 21996 | S23: Alfredo Jose Nieto | T23: Avenida de Los Corrales 7101 | U23: Mataderos | V23: Capital Federal | Y23: 38709841P - ARIAS PR PM, BRIAN EMANUEL | AB23: 46148 | AC23: 79969 | AF23: 46149 | AG23: 46148.84 | AK23: 0 | AM23: Tipo domicilio: Comercial. PB Referencia: maxikiosco Entre: Guamini y Montiel | AN23: Tipo domicilio: Comercial. PB Referencia: maxikiosco Entre: Guamini y Montiel | AQ23: tiendaobjetos | AR23: 32,64 | AS23: 32.64 | AX23: PAQUETERIA | BA23: 1440 | BE23: SMARTPOST | BF23: ESTADO FINAL | BG23: Tipo domicilio: Comercial. PB Referencia: maxikiosco Entre: Guamini y Montiel | BJ23: XXXXXXX | BK23: 46148.841 | BN23: 46148.582 | BO23: Pedido creado desde mercadoflex. Api v2 | BP23: ORIGEN | BS23: CABA C9 | BT23: CABA C9 | BU23: Tienda Objetos | BW23: Mflex
A24: 5533092 | B24: 46148 | C24: ZETABURGOS SRL | D24: TIENDA OBJETOS SUC. CABA | E24: POD-ENTREGADA | F24: Cambio notificado por MFLEX | G24: 47003053030 | H24: 2000012842929149 | I24: FLEX | N24: 0.36 | O24: 1 | P24: 9426.31 | Q24: 24684 | S24: Berenice nieva | T24: Lavalle 2754 | U24: San Vicente | V24: Buenos Aires | Y24: 42089762 - ARRUA, LEANDRO | AB24: 46148 | AC24: 80037 | AF24: 46149 | AG24: 46148.806 | AK24: 0 | AM24: Tipo domicilio: Particular. Al lado Casa Mi sueÃ± Referencia: llamar al numero de contacto 1150501207,entre carulli y corti en frente del campo, al lado casa con pileta y tranquera | AN24: Tipo domicilio: Particular. Al lado Casa Mi sueÃ± Referencia: llamar al numero de contacto 1150501207,entre carulli y corti en frente del campo, al lado casa con pileta y tranquera | AQ24: tiendaobjetos | AR24: 0,51975 | AS24: 0.51975 | AX24: PAQUETERIA | BA24: 1865 | BE24: SMARTPOST | BF24: ESTADO FINAL | BG24: Tipo domicilio: Particular. Al lado Casa Mi sueÃ± Referencia: llamar al numero de contacto 1150501207,entre carulli y corti en frente del campo, al lado casa con pileta y tranquera | BJ24: XXXXXXX | BK24: 46148.807 | BN24: 46148.651 | BO24: Pedido creado desde mercadoflex. Api v2 | BP24: ORIGEN | BS24: SUR S3 | BT24: San Vicente | BU24: Tienda Objetos | BW24: Mflex
A25: 5533132 | B25: 46148 | C25: ZETABURGOS SRL | D25: TIENDA OBJETOS SUC. CABA | E25: POD-ENTREGADA | F25: Cambio notificado por MFLEX | G25: 47002843643 | H25: 2000012843058489 | I25: FLEX | N25: 34.92 | O25: 6 | P25: 8709.92 | Q25: 47070 | S25: Rodrigo Garcia | T25: Calle Moreno 625 | U25: Quilmes | V25: Buenos Aires | Y25: 48645590 - RAMIREZ, NICOLAS DANIEL | AB25: 46148 | AC25: 79971 | AF25: 46149 | AG25: 46148.8 | AK25: 0 | AM25: Tipo domicilio: Comercial. Referencia: Local Arredo Entre: Alem Y Rivadavia | AN25: Tipo domicilio: Comercial. Referencia: Local Arredo Entre: Alem Y Rivadavia | AQ25: tiendaobjetos | AR25: 71,82 | AS25: 71.82 | AX25: PAQUETERIA | BA25: 1878 | BE25: SMARTPOST | BF25: ESTADO FINAL | BG25: Tipo domicilio: Comercial. Referencia: Local Arredo Entre: Alem Y Rivadavia | BJ25: XXXXXXX | BK25: 46148.8 | BN25: 46148.651 | BO25: Pedido creado desde mercadoflex. Api v2 | BP25: ORIGEN | BS25: SUR S2 | BT25: Quilmes | BU25: Tienda Objetos | BW25: Mflex
A26: 5533250 | B26: 46148 | C26: ZETABURGOS SRL | D26: TIENDA OBJETOS SUC. CABA | E26: POD-ENTREGADA | F26: Cambio notificado por MFLEX | G26: 47002957697 | H26: 2000012843309425 | I26: FLEX | N26: 0.32 | O26: 1 | P26: 8709.92 | Q26: 27618 | S26: Roberto Kohlhuber | T26: Intendente Pedro Oliveri 796 | U26: Quilmes | V26: Buenos Aires | Y26: 48645590 - RAMIREZ, NICOLAS DANIEL | AB26: 46148 | AC26: 79971 | AF26: 46149 | AG26: 46148.851 | AK26: 0 | AM26: Tipo domicilio: Particular. Referencia: Olivieri esquina Torcuato de Alvear Entre: Torcuato de Alvear y AndrÃ©s Baranda | AN26: Tipo domicilio: Particular. Referencia: Olivieri esquina Torcuato de Alvear Entre: Torcuato de Alvear y AndrÃ©s Baranda | AQ26: tiendaobjetos | AR26: 1,16 | AS26: 1.16 | AX26: PAQUETERIA | BA26: 1878 | BE26: SMARTPOST | BF26: ESTADO FINAL | BG26: Tipo domicilio: Particular. Referencia: Olivieri esquina Torcuato de Alvear Entre: Torcuato de Alvear y AndrÃ©s Baranda | BJ26: XXXXXXX | BK26: 46148.851 | BN26: 46148.651 | BO26: Pedido creado desde mercadoflex. Api v2 | BP26: ORIGEN | BS26: SUR S2 | BT26: Quilmes | BU26: Tienda Objetos | BW26: Mflex
A27: 5533267 | B27: 46148 | C27: ZETABURGOS SRL | D27: TIENDA OBJETOS SUC. CABA | E27: POD-ENTREGADA | F27: Cambio notificado por MFLEX | G27: 47002975633 | H27: 2000012843340519 | I27: FLEX | N27: 20 | O27: 5 | P27: 3919.34 | Q27: 31450 | S27: Carolina Gabriela Cordara | T27: Calle Jose de Amenabar 2249 | U27: Belgrano | V27: Capital Federal | Y27: 38199389 - ECHENIQUE, FEDERICO | AB27: 46148 | AC27: 80043 | AF27: 46149 | AG27: 46148.777 | AK27: 0 | AM27: Tipo domicilio: Particular. 2 do 10 Referencia: Es 2 do 10 - Amenbar | AN27: Tipo domicilio: Particular. 2 do 10 Referencia: Es 2 do 10 - Amenbar | AQ27: tiendaobjetos | AR27: 5,25 | AS27: 20 | AX27: PAQUETERIA | BA27: 1428 | BE27: SMARTPOST | BF27: ESTADO FINAL | BG27: Tipo domicilio: Particular. 2 do 10 Referencia: Es 2 do 10 - Amenbar | BJ27: XXXXXXX | BK27: 46148.777 | BN27: 46148.651 | BO27: Pedido creado desde mercadoflex. Api v2 | BP27: ORIGEN | BS27: CABA C12 | BT27: CABA C12 | BU27: Tienda Objetos | BW27: Mflex
A28: 5533282 | B28: 46148 | C28: ZETABURGOS SRL | D28: TIENDA OBJETOS SUC. CABA | E28: POD-ENTREGADA | F28: Cambio notificado por MFLEX | G28: 47003272760 | H28: 2000012843399887 | I28: FLEX | N28: 12.75 | O28: 5 | P28: 3919.34 | Q28: 364220 | S28: Delfina Martignone | T28: Avenida del Libertador 5665 | U28: Belgrano | V28: Capital Federal | Y28: 23327646 - GANDINI, LEONARDO | AB28: 46148 | AC28: 79897 | AF28: 46149 | AG28: 46148.781 | AK28: 0 | AM28: Tipo domicilio: Particular. 1F | AN28: Tipo domicilio: Particular. 1F | AQ28: tiendaobjetos | AR28: 11,025 | AS28: 12.75 | AX28: PAQUETERIA | BA28: 1426 | BF28: ESTADO FINAL | BG28: Tipo domicilio: Particular. 1F | BJ28: XXXXXXX | BK28: 46148.781 | BN28: 46148.651 | BO28: Pedido creado desde mercadoflex. Api v2 | BP28: ORIGEN | BS28: CABA C14 | BT28: CABA C14 | BU28: Tienda Objetos | BW28: Mflex
A29: 5533415 | B29: 46148 | C29: ZETABURGOS SRL | D29: TIENDA OBJETOS SUC. CABA | E29: POD-ENTREGADA | F29: Cambio notificado por MFLEX | G29: 47003386430 | H29: 2000016301616080 | I29: FLEX | N29: 0.44 | O29: 1 | P29: 3919.34 | Q29: 5480 | S29: Federico garcia | T29: Calle Doctor Luis Belaustegui 4825 | U29: Floresta | V29: Capital Federal | Y29: 36954970 - ALBORNOZ, SERGIO | AB29: 46148 | AC29: 79958 | AF29: 46149 | AG29: 46148.799 | AK29: 0 | AM29: Tipo domicilio: Particular. Entre: Bermudez y pasaje Emilio Castelar | AN29: Tipo domicilio: Particular. Entre: Bermudez y pasaje Emilio Castelar | AQ29: tiendaobjetos | AR29: 0,529 | AS29: 0.529 | AX29: PAQUETERIA | BA29: 1407 | BE29: SMARTPOST | BF29: ESTADO FINAL | BG29: Tipo domicilio: Particular. Entre: Bermudez y pasaje Emilio Castelar | BJ29: XXXXXXX | BK29: 46148.8 | BN29: 46148.651 | BO29: Pedido creado desde mercadoflex. Api v2 | BP29: ORIGEN | BS29: CABA C11 | BT29: CABA C11 | BU29: Tienda Objetos | BW29: Mflex
A30: 5533481 | B30: 46148 | C30: ZETABURGOS SRL | D30: TIENDA OBJETOS SUC. CABA | E30: POD-ENTREGADA | F30: Cambio notificado por MFLEX | G30: 47003169265 | H30: 2000012843766303 | I30: FLEX | N30: 0.72 | O30: 3 | P30: 8709.92 | Q30: 23547 | S30: Rosario egaÃ±a | T30: Corredor bancalari 3901 | U30: General Pacheco | V30: Buenos Aires | Y30: 50011998 - PFAFFENCELLER - FLOTA DISTRI MAC, AMANDA VICTORIA | AB30: 46148 | AC30: 80020 | AF30: 46149 | AG30: 46148.831 | AK30: 0 | AM30: Tipo domicilio: Particular. Lote 433 Entre: Barrio santa barbara | AN30: Tipo domicilio: Particular. Lote 433 Entre: Barrio santa barbara | AQ30: tiendaobjetos | AR30: 2,142 | AS30: 2.142 | AX30: PAQUETERIA | BA30: 1617 | BF30: ESTADO FINAL | BG30: Tipo domicilio: Particular. Lote 433 Entre: Barrio santa barbara | BJ30: XXXXXXX | BK30: 46148.831 | BN30: 46148.651 | BO30: Pedido creado desde mercadoflex. Api v2 | BP30: ORIGEN | BS30: NORTE N2 | BT30: General Pacheco | BU30: Tienda Objetos | BW30: Mflex
A31: 5533483 | B31: 46148 | C31: ZETABURGOS SRL | D31: TIENDA OBJETOS SUC. CABA | E31: POD-ENTREGADA | F31: Cambio notificado por MFLEX | G31: 47003446316 | H31: 2000012843781391 | I31: FLEX | N31: 11.16 | O31: 2 | P31: 3919.34 | Q31: 138349.62 | S31: Matias Luthard | T31: Calle Thames 2313 | U31: Palermo | V31: Capital Federal | Y31: 33061061 - SORIA-FLOTA GRUPO MAF, DAMIAN LUCIO | AB31: 46148 | AC31: 80049 | AF31: 46149 | AG31: 46148.845 | AK31: 0 | AM31: Tipo domicilio: Comercial. 604 | AN31: Tipo domicilio: Comercial. 604 | AQ31: tiendaobjetos | AR31: 20,286 | AS31: 20.286 | AX31: PAQUETERIA | BA31: 1425 | BE31: SMARTPOST | BF31: ESTADO FINAL | BG31: Tipo domicilio: Comercial. 604 | BJ31: XXXXXXX | BK31: 46148.846 | BN31: 46148.651 | BO31: Pedido creado desde mercadoflex. Api v2 | BP31: ORIGEN | BS31: CABA C14 | BT31: CABA C14 | BU31: Tienda Objetos | BW31: Mflex
A32: 5534010 | B32: 46148 | C32: ZETABURGOS SRL | D32: TIENDA OBJETOS SUC. CABA | E32: POD-ENTREGADA | F32: Cambio notificado por MFLEX | G32: 47003796464 | H32: 2000012844544889 | I32: FLEX | N32: 1.22 | O32: 2 | P32: 6265.34 | Q32: 25042 | S32: carlos bartozyk | T32: Calle Teniente Coronel Jorge Obon 2549 | U32: LanÃºs | V32: Buenos Aires | Y32: 38587811 - ACHAVAL, ARIAN | AB32: 46148 | AC32: 79961 | AF32: 46149 | AG32: 46148.747 | AK32: 0 | AM32: Tipo domicilio: Particular. Entre: masa y emilio castro | AN32: Tipo domicilio: Particular. Entre: masa y emilio castro | AQ32: tiendaobjetos | AR32: 4,9875 | AS32: 4.9875 | AX32: PAQUETERIA | BA32: 1824 | BE32: SMARTPOST | BF32: ESTADO FINAL | BG32: Tipo domicilio: Particular. Entre: masa y emilio castro | BJ32: XXXXXXX | BK32: 46148.747 | BN32: 46148.651 | BO32: Pedido creado desde mercadoflex. Api v2 | BP32: ORIGEN | BS32: SUR S1 | BT32: Lanus | BU32: Tienda Objetos | BW32: Mflex
A33: 5534025 | B33: 46148 | C33: ZETABURGOS SRL | D33: TIENDA OBJETOS SUC. CABA | E33: POD-ENTREGADA | G33: 47003546681 | H33: 2000012844605281 | I33: FLEX | N33: 1.85 | O33: 1 | P33: 3919.34 | Q33: 51995 | S33: Leonardo Javier Crugley | T33: Calle Marcos Riglos 957 | U33: Parque Chacabuco | V33: Capital Federal | Y33: 34693651P - CHAPARRO PR PM, RAMON | AB33: 46148 | AC33: 79944 | AF33: 46149 | AG33: 46148.815 | AH33: Leonardo Javier Crugley | AK33: 0 | AM33: Tipo domicilio: Comercial. Referencia: Laboratorio de Essayos Fisicoquimicos - PFA - Riglos | AN33: Tipo domicilio: Comercial. Referencia: Laboratorio de Essayos Fisicoquimicos - PFA - Riglos | AQ33: tiendaobjetos | AR33: 5,56875 | AS33: 5.56875 | AX33: PAQUETERIA | BA33: 1424 | BE33: SMARTPOST | BF33: ESTADO FINAL | BG33: Tipo domicilio: Comercial. Referencia: Laboratorio de Essayos Fisicoquimicos - PFA - Riglos | BJ33: XXXXXXX | BK33: 46148.815 | BN33: 46148.651 | BO33: Pedido creado desde mercadoflex. Api v2 | BP33: ORIGEN | BS33: CABA C4 | BT33: CABA C4 | BU33: Tienda Objetos | BW33: Mflex
A34: 5534036 | B34: 46148 | C34: ZETABURGOS SRL | D34: TIENDA OBJETOS SUC. CABA | E34: POD-ENTREGADA | F34: Cambio notificado por MFLEX | G34: 47003067298 | H34: 2000012842953845 | I34: FLEX | N34: 3.2 | O34: 2 | P34: 9426.31 | Q34: 61634 | S34: Manuel Soria | T34: Boulevard de Todos los Santos 3500 | U34: Dique LujÃ¡n | V34: Buenos Aires | Y34: 41768386 - GONZALEZ, CESAR NAHUEL | AB34: 46148 | AC34: 79900 | AF34: 46149 | AG34: 46148.778 | AK34: 0 | AM34: Tipo domicilio: Particular. 348 Referencia: 359 | AN34: Tipo domicilio: Particular. 348 Referencia: 359 | AQ34: tiendaobjetos | AR34: 0,55 | AS34: 3.2 | AX34: PAQUETERIA | BA34: 1622 | BF34: ESTADO FINAL | BG34: Tipo domicilio: Particular. 348 Referencia: 359 | BJ34: XXXXXXX | BK34: 46148.778 | BN34: 46148.651 | BO34: Pedido creado desde mercadoflex. Api v2 | BP34: ORIGEN | BS34: NORTE N2B | BT34: Dique Lujan | BU34: Tienda Objetos | BW34: Mflex
A35: 5534280 | B35: 46148 | C35: ZETABURGOS SRL | D35: TIENDA OBJETOS SUC. CABA | E35: POD-ENTREGADA | F35: Cambio notificado por MFLEX | G35: 47003721201 | H35: 2000012844980431 | I35: FLEX | N35: 1.4 | O35: 2 | P35: 6265.34 | Q35: 20074 | S35: Karina Aurnague | T35: Calle Larrea 1132 | U35: Ramos mejia | V35: Buenos Aires | Y35: 39375501P - SOSA PR PM, MARIANO NICOLAS | AB35: 46148 | AC35: 79938 | AF35: 46149 | AG35: 46148.865 | AK35: 0 | AM35: Tipo domicilio: Particular. Referencia: Llamar Por Telefono, No Anda El Timbre Entre: O Ghighins y Chubut | AN35: Tipo domicilio: Particular. Referencia: Llamar Por Telefono, No Anda El Timbre Entre: O Ghighins y Chubut | AQ35: tiendaobjetos | AR35: 4,992 | AS35: 4.992 | AX35: PAQUETERIA | BA35: 1704 | BE35: SMARTPOST | BF35: ESTADO FINAL | BG35: Tipo domicilio: Particular. Referencia: Llamar Por Telefono, No Anda El Timbre Entre: O Ghighins y Chubut | BJ35: XXXXXXX | BK35: 46148.865 | BN35: 46148.651 | BO35: Pedido creado desde mercadoflex. Api v2 | BP35: ORIGEN | BS35: OESTE O1 | BT35: Ramos Mejia | BU35: Tienda Objetos | BW35: Mflex
A36: 5534617 | B36: 46148 | C36: ZETABURGOS SRL | D36: TIENDA OBJETOS SUC. CABA | E36: POD-ENTREGADA | F36: Cambio notificado por MFLEX | G36: 47004473504 | H36: 2000016303906044 | I36: FLEX | N36: 0.38 | O36: 1 | P36: 3919.34 | Q36: 13801 | S36: Agustina Vila | T36: Calle Hualfin 891 | U36: Caballito | V36: Capital Federal | Y36: 44925898 - CABRERA, DANIEL | AB36: 46148 | AC36: 80036 | AF36: 46149 | AG36: 46148.851 | AK36: 0 | AM36: Tipo domicilio: Particular. 1 A Referencia: 1 A | AN36: Tipo domicilio: Particular. 1 A Referencia: 1 A | AQ36: tiendaobjetos | AR36: 1,24775 | AS36: 1.24775 | AX36: PAQUETERIA | BA36: 1424 | BE36: SMARTPOST | BF36: ESTADO FINAL | BG36: Tipo domicilio: Particular. 1 A Referencia: 1 A | BJ36: XXXXXXX | BK36: 46148.851 | BN36: 46148.651 | BO36: Pedido creado desde mercadoflex. Api v2 | BP36: ORIGEN | BS36: CABA C4 | BT36: CABA C4 | BU36: Tienda Objetos | BW36: Mflex

Sheet aux
A1: VISITA COORDINADA CON EL CLIENTE
A2: N/A
A3: CERRADO EN APP FLEX
